lightning_fabric/CHANGELOG.md
lightning_fabric/__about__.py
lightning_fabric/__init__.py
lightning_fabric/__setup__.py
lightning_fabric/__version__.py
lightning_fabric/cli.py
lightning_fabric/connector.py
lightning_fabric/fabric.py
lightning_fabric/py.typed
lightning_fabric/version.info
lightning_fabric/wrappers.py
lightning_fabric/_graveyard/__init__.py
lightning_fabric/_graveyard/tpu.py
lightning_fabric/accelerators/__init__.py
lightning_fabric/accelerators/accelerator.py
lightning_fabric/accelerators/cpu.py
lightning_fabric/accelerators/cuda.py
lightning_fabric/accelerators/mps.py
lightning_fabric/accelerators/registry.py
lightning_fabric/accelerators/xla.py
lightning_fabric/loggers/__init__.py
lightning_fabric/loggers/csv_logs.py
lightning_fabric/loggers/logger.py
lightning_fabric/loggers/tensorboard.py
lightning_fabric/plugins/__init__.py
lightning_fabric/plugins/collectives/__init__.py
lightning_fabric/plugins/collectives/collective.py
lightning_fabric/plugins/collectives/single_device.py
lightning_fabric/plugins/collectives/torch_collective.py
lightning_fabric/plugins/environments/__init__.py
lightning_fabric/plugins/environments/cluster_environment.py
lightning_fabric/plugins/environments/kubeflow.py
lightning_fabric/plugins/environments/lightning.py
lightning_fabric/plugins/environments/lsf.py
lightning_fabric/plugins/environments/mpi.py
lightning_fabric/plugins/environments/slurm.py
lightning_fabric/plugins/environments/torchelastic.py
lightning_fabric/plugins/environments/xla.py
lightning_fabric/plugins/io/__init__.py
lightning_fabric/plugins/io/checkpoint_io.py
lightning_fabric/plugins/io/torch_io.py
lightning_fabric/plugins/io/xla.py
lightning_fabric/plugins/precision/__init__.py
lightning_fabric/plugins/precision/amp.py
lightning_fabric/plugins/precision/bitsandbytes.py
lightning_fabric/plugins/precision/deepspeed.py
lightning_fabric/plugins/precision/double.py
lightning_fabric/plugins/precision/fsdp.py
lightning_fabric/plugins/precision/half.py
pytorch_lightning-2.5.4.dist-info/licenses/LICENSE
pytorch_lightning-2.5.4.dist-info/METADATA
pytorch_lightning-2.5.4.dist-info/WHEEL
pytorch_lightning-2.5.4.dist-info/top_level.txt
pytorch_lightning-2.5.4.dist-info/RECORD
