Metadata-Version: 2.4
Name: pytorch-lightning
Version: 2.5.4
Summary: PyTorch Lightning is the lightweight PyTorch wrapper for ML researchers. Scale your models. Write less boilerplate.
Home-page: https://github.com/Lightning-AI/lightning
Download-URL: https://github.com/Lightning-AI/lightning
Author: Lightning AI et al.
Author-email: developer@lightning.ai
License: Apache-2.0
Project-URL: Bug Tracker, https://github.com/Lightning-AI/pytorch-lightning/issues
Project-URL: Documentation, https://pytorch-lightning.rtfd.io/en/latest/
Project-URL: Source Code, https://github.com/Lightning-AI/lightning
Keywords: deep learning,pytorch,AI
Classifier: Environment :: Console
Classifier: Natural Language :: English
Classifier: Development Status :: 5 - Production/Stable
Classifier: Intended Audience :: Developers
Classifier: Topic :: Scientific/Engineering :: Artificial Intelligence
Classifier: Topic :: Scientific/Engineering :: Image Recognition
Classifier: Topic :: Scientific/Engineering :: Information Analysis
Classifier: License :: OSI Approved :: Apache Software License
Classifier: Operating System :: OS Independent
Classifier: Programming Language :: Python :: 3
Classifier: Programming Language :: Python :: 3.9
Classifier: Programming Language :: Python :: 3.10
Classifier: Programming Language :: Python :: 3.11
Classifier: Programming Language :: Python :: 3.12
Requires-Python: >=3.9
License-File: LICENSE
Requires-Dist: torch>=2.1.0
Requires-Dist: tqdm>=4.57.0
Requires-Dist: PyYAML>5.4
Requires-Dist: fsspec[http]>=2022.5.0
Requires-Dist: torchmetrics>0.7.0
Requires-Dist: packaging>=20.0
Requires-Dist: typing-extensions>4.5.0
Requires-Dist: lightning-utilities>=0.10.0
Provides-Extra: extra
Requires-Dist: matplotlib>3.1; extra == "extra"
Requires-Dist: omegaconf>=2.2.3; extra == "extra"
Requires-Dist: hydra-core>=1.2.0; extra == "extra"
Requires-Dist: jsonargparse[jsonnet,signatures]>=4.39.0; extra == "extra"
Requires-Dist: rich>=12.3.0; extra == "extra"
Requires-Dist: tensorboardX>=2.2; extra == "extra"
Requires-Dist: bitsandbytes>=0.45.2; platform_system != "Darwin" and extra == "extra"
Provides-Extra: strategies
Requires-Dist: deepspeed<=0.15.0,>=0.14.1; (platform_system != "Windows" and platform_system != "Darwin") and extra == "strategies"
Provides-Extra: test
Requires-Dist: coverage==7.10.5; extra == "test"
Requires-Dist: pytest==8.4.1; extra == "test"
Requires-Dist: pytest-cov==6.2.1; extra == "test"
Requires-Dist: pytest-timeout==2.4.0; extra == "test"
Requires-Dist: pytest-rerunfailures==15.1; extra == "test"
Requires-Dist: pytest-random-order==1.2.0; extra == "test"
Requires-Dist: cloudpickle>=1.3; extra == "test"
Requires-Dist: scikit-learn>0.22.1; extra == "test"
Requires-Dist: numpy>1.20.0; extra == "test"
Requires-Dist: onnx>1.12.0; extra == "test"
Requires-Dist: onnxruntime>=1.12.0; extra == "test"
Requires-Dist: onnxscript>=0.1.0; extra == "test"
Requires-Dist: psutil<7.0.1; extra == "test"
Requires-Dist: pandas>2.0; extra == "test"
Requires-Dist: fastapi; extra == "test"
Requires-Dist: uvicorn; extra == "test"
Requires-Dist: tensorboard>=2.11; extra == "test"
Provides-Extra: examples
Requires-Dist: requests<2.33.0; extra == "examples"
Requires-Dist: torchvision>=0.16.0; extra == "examples"
Requires-Dist: ipython[all]<8.19.0; extra == "examples"
Requires-Dist: torchmetrics>=0.10.0; extra == "examples"
Provides-Extra: deepspeed
Requires-Dist: deepspeed<=0.15.0,>=0.14.1; (platform_system != "Windows" and platform_system != "Darwin") and extra == "deepspeed"
Provides-Extra: all
Requires-Dist: matplotlib>3.1; extra == "all"
Requires-Dist: omegaconf>=2.2.3; extra == "all"
Requires-Dist: hydra-core>=1.2.0; extra == "all"
Requires-Dist: jsonargparse[jsonnet,signatures]>=4.39.0; extra == "all"
Requires-Dist: rich>=12.3.0; extra == "all"
Requires-Dist: tensorboardX>=2.2; extra == "all"
Requires-Dist: bitsandbytes>=0.45.2; platform_system != "Darwin" and extra == "all"
Requires-Dist: deepspeed<=0.15.0,>=0.14.1; (platform_system != "Windows" and platform_system != "Darwin") and extra == "all"
Requires-Dist: requests<2.33.0; extra == "all"
Requires-Dist: torchvision>=0.16.0; extra == "all"
Requires-Dist: ipython[all]<8.19.0; extra == "all"
Requires-Dist: torchmetrics>=0.10.0; extra == "all"
Provides-Extra: dev
Requires-Dist: matplotlib>3.1; extra == "dev"
Requires-Dist: omegaconf>=2.2.3; extra == "dev"
Requires-Dist: hydra-core>=1.2.0; extra == "dev"
Requires-Dist: jsonargparse[jsonnet,signatures]>=4.39.0; extra == "dev"
Requires-Dist: rich>=12.3.0; extra == "dev"
Requires-Dist: tensorboardX>=2.2; extra == "dev"
Requires-Dist: bitsandbytes>=0.45.2; platform_system != "Darwin" and extra == "dev"
Requires-Dist: deepspeed<=0.15.0,>=0.14.1; (platform_system != "Windows" and platform_system != "Darwin") and extra == "dev"
Requires-Dist: requests<2.33.0; extra == "dev"
Requires-Dist: torchvision>=0.16.0; extra == "dev"
Requires-Dist: ipython[all]<8.19.0; extra == "dev"
Requires-Dist: torchmetrics>=0.10.0; extra == "dev"
Requires-Dist: coverage==7.10.5; extra == "dev"
Requires-Dist: pytest==8.4.1; extra == "dev"
Requires-Dist: pytest-cov==6.2.1; extra == "dev"
Requires-Dist: pytest-timeout==2.4.0; extra == "dev"
Requires-Dist: pytest-rerunfailures==15.1; extra == "dev"
Requires-Dist: pytest-random-order==1.2.0; extra == "dev"
Requires-Dist: cloudpickle>=1.3; extra == "dev"
Requires-Dist: scikit-learn>0.22.1; extra == "dev"
Requires-Dist: numpy>1.20.0; extra == "dev"
Requires-Dist: onnx>1.12.0; extra == "dev"
Requires-Dist: onnxruntime>=1.12.0; extra == "dev"
Requires-Dist: onnxscript>=0.1.0; extra == "dev"
Requires-Dist: psutil<7.0.1; extra == "dev"
Requires-Dist: pandas>2.0; extra == "dev"
Requires-Dist: fastapi; extra == "dev"
Requires-Dist: uvicorn; extra == "dev"
Requires-Dist: tensorboard>=2.11; extra == "dev"
Dynamic: author
Dynamic: author-email
Dynamic: classifier
Dynamic: description
Dynamic: description-content-type
Dynamic: download-url
Dynamic: home-page
Dynamic: keywords
Dynamic: license
Dynamic: license-file
Dynamic: project-url
Dynamic: provides-extra
Dynamic: requires-dist
Dynamic: requires-python
Dynamic: summary
